__init__.py
_types.py
constants.py
errors.py
functions.py
pymathematic-0.0.1.dist-info/LICENSE
pymathematic-0.0.1.dist-info/METADATA
pymathematic-0.0.1.dist-info/WHEEL
pymathematic-0.0.1.dist-info/top_level.txt
pymathematic-0.0.1.dist-info/RECORD
