Metadata-Version: 2.1
Name: pymathematic
Version: 0.0.1
Summary: A better Python package for math.
Author-email: foxypiratecove37350 <foxypiratecove12@gmail.com>
License: GNU GENERAL PUBLIC LICENSE
Project-URL: Homepage, https://github.com/foxypiratecove37350/pymathematic
Project-URL: Issues, https://github.com/foxypiratecove37350/pymathematic/issues
Classifier: Programming Language :: Python :: 3
Classifier: License :: OSI Approved :: GNU General Public License v2 (GPLv2)
Classifier: Operating System :: OS Independent
Requires-Python: >=3.12
License-File: LICENSE
